{"3459": {"global": [{"cpu-cycles": 14278961583, "instructions": 16078457573, "cache-references": 1333780285, "cache-misses": 10956758, "LLC-loads": 98148102, "LLC-load-misses": 680028, "LLC-store-misses": 2115004, "LLC-stores": 24687307, "L1-dcache-load-misses": 225730437, "L1-dcache-loads": 5205012981, "L1-dcache-stores": 2617048808, "GPU_Util": 0.99, "GPU_Mem": 0.69}], "model-sons": [{"cpu-cycles": 4644973850, "instructions": 4626706142, "cache-references": 472823173, "cache-misses": 1066166, "LLC-loads": 36724274, "LLC-load-misses": 90146, "LLC-store-misses": 48618, "LLC-stores": 8252965, "L1-dcache-load-misses": 94019371, "L1-dcache-loads": 1499211549, "L1-dcache-stores": 795989487, "GPU_Util": 0.99, "GPU_Mem": 0.69, "name": "googlenet"}, {"cpu-cycles": 4622361743, "instructions": 5189115416, "cache-references": 391043541, "cache-misses": 835445, "LLC-loads": 26573822, "LLC-load-misses": 76317, "LLC-store-misses": 12530, "LLC-stores": 7298895, "L1-dcache-load-misses": 82817553, "L1-dcache-loads": 1742716808, "L1-dcache-stores": 896196828, "GPU_Util": 0.99, "GPU_Mem": 0.69, "name": "squeezenet"}, {"cpu-cycles": 4634378525, "instructions": 3179453264, "cache-references": 668177800, "cache-misses": 766898, "LLC-loads": 50612258, "LLC-load-misses": 68179, "LLC-store-misses": 61954, "LLC-stores": 11262743, "L1-dcache-load-misses": 104140679, "L1-dcache-loads": 980543229, "L1-dcache-stores": 549151919, "GPU_Util": 0.99, "GPU_Mem": 0.69, "name": "mobilenet_v3_large"}], "inference-model-info": 1, "inference-model-sys-info": {"GPU_Util": 0.97, "GPU_Mem": 0.69}, "inference-model-latency": 29.423129999999993, "inference-model-name": "inception_v3"}}