{"5963": {"global": [{"cpu-cycles": 14726740373, "instructions": 18834940876, "cache-references": 980194739, "cache-misses": 51661051, "LLC-loads": 82409568, "LLC-load-misses": 5777285, "LLC-store-misses": 10762956, "LLC-stores": 31016819, "L1-dcache-load-misses": 241972028, "L1-dcache-loads": 6119451399, "L1-dcache-stores": 3121910654, "GPU_Util": 0.99, "GPU_Mem": 0.77}], "model-sons": [{"cpu-cycles": 4628712990, "instructions": 3228690509, "cache-references": 649484155, "cache-misses": 1223771, "LLC-loads": 49810010, "LLC-load-misses": 85531, "LLC-store-misses": 57339, "LLC-stores": 11374799, "L1-dcache-load-misses": 103553347, "L1-dcache-loads": 1002266649, "L1-dcache-stores": 562637792, "GPU_Util": 0.99, "GPU_Mem": 0.77, "name": "shufflenet"}, {"cpu-cycles": 4640970443, "instructions": 8288349805, "cache-references": 45282581, "cache-misses": 428570, "LLC-loads": 3196368, "LLC-load-misses": 37316, "LLC-store-misses": 5986, "LLC-stores": 726212, "L1-dcache-load-misses": 79919844, "L1-dcache-loads": 2848581010, "L1-dcache-stores": 1448420034, "GPU_Util": 0.99, "GPU_Mem": 0.77, "name": "vgg_16"}, {"cpu-cycles": 4629827180, "instructions": 7321373506, "cache-references": 116176012, "cache-misses": 497774, "LLC-loads": 8458197, "LLC-load-misses": 46783, "LLC-store-misses": 33935, "LLC-stores": 2030482, "L1-dcache-load-misses": 70708092, "L1-dcache-loads": 2491089637, "L1-dcache-stores": 1277422106, "GPU_Util": 0.99, "GPU_Mem": 0.77, "name": "alexnet"}], "inference-model-info": 1, "inference-model-sys-info": {"GPU_Util": 0.99, "GPU_Mem": 0.77}, "inference-model-latency": 5.1744200000000005, "inference-model-name": "mobilenet_v3_large"}}