{"780": {"global": [{"cpu-cycles": 9594152238, "instructions": 10944485264, "cache-references": 785340156, "cache-misses": 25777501, "LLC-loads": 61869991, "LLC-load-misses": 3021109, "LLC-store-misses": 6004177, "LLC-stores": 18498923, "L1-dcache-load-misses": 199688115, "L1-dcache-loads": 3541089412, "L1-dcache-stores": 1867446765, "GPU_Util": 0.38, "GPU_Mem": 0.6}], "model-sons": [{"cpu-cycles": 4671784355, "instructions": 3154047116, "cache-references": 637032706, "cache-misses": 636158, "LLC-loads": 47622878, "LLC-load-misses": 74963, "LLC-store-misses": 48896, "LLC-stores": 11115286, "L1-dcache-load-misses": 100338516, "L1-dcache-loads": 977351260, "L1-dcache-stores": 547889682, "GPU_Util": 0.99, "GPU_Mem": 0.6, "name": "shufflenet"}, {"cpu-cycles": 4659574618, "instructions": 8001272794, "cache-references": 92782036, "cache-misses": 521498, "LLC-loads": 6622226, "LLC-load-misses": 32079, "LLC-store-misses": 1173, "LLC-stores": 1740206, "L1-dcache-load-misses": 85423002, "L1-dcache-loads": 2728232418, "L1-dcache-stores": 1394862071, "GPU_Util": 0.99, "GPU_Mem": 0.6, "name": "vgg_13"}], "inference-model-info": 1, "inference-model-sys-info": {"GPU_Util": 0.99, "GPU_Mem": 0.6}, "inference-model-latency": 8.58442, "inference-model-name": "mvit"}}