{"659": {"global": [{"cpu-cycles": 61566674166, "instructions": 29807710509, "cache-references": 1101353919, "cache-misses": 466413785, "LLC-loads": 181661879, "LLC-load-misses": 106155272, "LLC-store-misses": 100109642, "LLC-stores": 162156832, "L1-dcache-load-misses": 1161677582, "L1-dcache-loads": 9409579825, "L1-dcache-stores": 607214046, "CPU_Util": 100.0}], "model-sons": [{"cpu-cycles": 30628392316, "instructions": 15909850042, "cache-references": 415097072, "cache-misses": 113558848, "LLC-loads": 44421343, "LLC-load-misses": 7370688, "LLC-store-misses": 80598511, "LLC-stores": 130771222, "L1-dcache-load-misses": 448176889, "L1-dcache-loads": 4666404789, "L1-dcache-stores": 343962288, "CPU_Util": 99.9, "name": "squeezenet"}, {"cpu-cycles": 30765075621, "instructions": 12491843325, "cache-references": 691169556, "cache-misses": 353732908, "LLC-loads": 140638604, "LLC-load-misses": 103435174, "LLC-store-misses": 15486341, "LLC-stores": 42609536, "L1-dcache-load-misses": 771595448, "L1-dcache-loads": 4491372318, "L1-dcache-stores": 251212977, "CPU_Util": 100.0, "name": "alexnet"}], "inference-model-info": 1, "inference-model-sys-info": {"CPU_Util": 100.0}, "inference-model-latency": 1348.0016333333335, "inference-model-name": "mvit"}}